cli/__init__.py
cli/api_client.py
cli/main.py
question_generator-0.1.11.dist-info/LICENSE
question_generator-0.1.11.dist-info/METADATA
question_generator-0.1.11.dist-info/WHEEL
question_generator-0.1.11.dist-info/entry_points.txt
question_generator-0.1.11.dist-info/top_level.txt
question_generator-0.1.11.dist-info/RECORD
