Metadata-Version: 2.1
Name: question-generator
Version: 0.1.11
Summary: A CLI tool for generating prompts from Notion templates
Home-page: https://github.com/devfactory/prompt-generator
Author: David Schwartz
Author-email: david.schwartz@devfactory.com
License: UNKNOWN
Platform: UNKNOWN
Classifier: Programming Language :: Python :: 3
Classifier: License :: OSI Approved :: MIT License
Classifier: Operating System :: OS Independent
Requires-Python: >=3.7
License-File: LICENSE
Requires-Dist: click>=8.0.0
Requires-Dist: aiohttp>=3.8.0
Requires-Dist: platformdirs>=3.0.0
